{
    "AS_Form_e57d4eabde4a4bb78d4952b3d5d9dc02": {
        "id": "AS_Form_e57d4eabde4a4bb78d4952b3d5d9dc02",
        "type": "ACTION_SEQUENCE",
        "params": [{
            "datatype": "collection",
            "name": "eventobject"
        }],
        "contextObj": {
            "name": "frmDashbord",
            "type": "forms",
            "platform": "",
            "KUID": "j24ee47617c5456698cbe52c276bbaa7"
        },
        "language": "js",
        "actions": [{
            "id": "MOVE_ACTION_a9125f896c534d58a9b5fe88d6fe9417",
            "type": "MOVE_ACTION",
            "itemType": "FORM",
            "itemId": "frmDashbord",
            "widgetId": "flxHumbergerMenu",
            "itemKUID": "j24ee47617c5456698cbe52c276bbaa7",
            "widgetKUID": "i95e2574705a484dbfbf4b9b38f5a284",
            "wType": "FlexContainer",
            "animationObject": {
                "centerX": "-100%",
                "anchorPoint": {},
                "stepConfig": {
                    "timingFunction": "kony.anim.EASE"
                }
            },
            "config": {
                "delay": "0",
                "iterationCount": 1,
                "fillMode": "kony.anim.FILL_MODE_FORWARDS",
                "duration": "250"
            },
            "start": "Immediately",
            "animationId": "MOVE_ACTION_a9125f896c534d58a9b5fe88d6fe9417",
            "displayAnimationId": "MOVE_ACTION_a9125f896c534d58a9b5fe88d6fe9417",
            "forkedPlatform": "all",
            "widgetPath": "this.view.flxHumbergerMenu"
        }]
    }
}